[
  {
    "id": "qi_xing_zhen",
    "name": "七星阵",
    "subType": "主动",
    "quality": "橙",
    "description": "对敌方群体造成谋略伤害(智力差影响),并使其受到的伤害提升,持续2回合。",
    "source": "诸葛亮自带",
    "sourceType": "自带",
    "carrierIds": ["zhuge_liang"],
    "triggerRate": 0.35,
    "multiTarget": true,
    "startRound": 1
  },
  {
    "id": "ren_de_zai_shi",
    "name": "仁德载世",
    "subType": "指挥",
    "quality": "橙",
    "description": "战斗开始后,每回合为我方群体恢复兵力(智力影响)。",
    "source": "刘备自带",
    "sourceType": "自带",
    "carrierIds": ["liu_bei"],
    "triggerRate": null,
    "multiTarget": true,
    "startRound": 1
  },
  {
    "id": "wan_ren_zhi_di",
    "name": "万人之敌",
    "subType": "指挥",
    "quality": "橙",
    "description": "对随机敌方单体造成兵刃伤害(武力差影响),并使其陷入缴械,持续1回合。",
    "source": "张飞自带",
    "sourceType": "自带",
    "carrierIds": ["zhang_fei"],
    "triggerRate": null,
    "multiTarget": false,
    "startRound": 1
  },
  {
    "id": "wei_zhen_hua_xia",
    "name": "威震华夏",
    "subType": "主动",
    "quality": "橙",
    "description": "对敌方群体造成兵刃伤害(武力差影响),并使其陷入缴械或计穷,持续1回合。",
    "source": "关羽自带",
    "sourceType": "自带",
    "carrierIds": ["guan_yu"],
    "triggerRate": 0.35,
    "multiTarget": true,
    "startRound": 1
  },
  {
    "id": "long_dan",
    "name": "龙胆",
    "subType": "被动",
    "quality": "橙",
    "description": "普攻后可获得连击并提升属性;受到伤害时有概率获得减伤/闪避。",
    "source": "赵云自带",
    "sourceType": "自带",
    "carrierIds": ["zhao_yun"],
    "triggerRate": null,
    "multiTarget": false,
    "startRound": 1
  },
  {
    "id": "kong_cheng_ji",
    "name": "空城计",
    "subType": "主动",
    "quality": "橙",
    "description": "对敌方单体造成谋略伤害(智力差影响),并使其陷入计穷,持续1回合。",
    "source": "诸葛亮传承",
    "sourceType": "传承",
    "carrierIds": ["zhuge_liang"],
    "triggerRate": 0.35,
    "multiTarget": false,
    "startRound": 1
  },
  {
    "id": "yi_xin_zhao_yong",
    "name": "义心昭勇",
    "subType": "主动",
    "quality": "橙",
    "description": "使我方群体受到的伤害降低(智力影响),持续2回合。",
    "source": "刘备传承",
    "sourceType": "传承",
    "carrierIds": ["liu_bei"],
    "triggerRate": 0.35,
    "multiTarget": true,
    "startRound": 1
  },
  {
    "id": "chen_mu_heng_mao",
    "name": "瞋目横矛",
    "subType": "主动",
    "quality": "橙",
    "description": "对敌方群体造成兵刃伤害(武力差影响),并使其陷入缴械,持续1回合。",
    "source": "张飞传承",
    "sourceType": "传承",
    "carrierIds": ["zhang_fei"],
    "triggerRate": 0.35,
    "multiTarget": true,
    "startRound": 1
  },
  {
    "id": "heng_sao_qian_jun",
    "name": "横扫千军",
    "subType": "突击",
    "quality": "橙",
    "description": "普通攻击后,对敌方群体造成兵刃伤害(武力差影响),并有概率使其陷入缴械。",
    "source": "关羽传承",
    "sourceType": "传承",
    "carrierIds": ["guan_yu", "zhao_yun"],
    "triggerRate": 0.35,
    "multiTarget": true,
    "startRound": 1
  },
  {
    "id": "tai_ping_dao_fa",
    "name": "太平道法",
    "subType": "主动",
    "quality": "橙",
    "description": "使自身获得必中和暴击属性(持续若干回合),并提升谋略伤害。",
    "source": "张角传承",
    "sourceType": "传承",
    "carrierIds": [],
    "triggerRate": 0.35,
    "multiTarget": false,
    "startRound": 1
  },
  {
    "id": "gua_gu_liao_du",
    "name": "刮骨疗毒",
    "subType": "主动",
    "quality": "橙",
    "description": "为损失兵力最多的我方单体移除负面状态,并恢复兵力(智力影响)。",
    "source": "关羽传承",
    "sourceType": "传承",
    "carrierIds": ["guan_yu"],
    "triggerRate": 0.35,
    "multiTarget": false,
    "startRound": 1
  },
  {
    "id": "yi_qi_li_ci",
    "name": "益其利词",
    "subType": "主动",
    "quality": "橙",
    "description": "使自身获得群攻、增伤属性(持续若干回合),并提升普攻伤害。",
    "source": "荀彧传承",
    "sourceType": "传承",
    "carrierIds": [],
    "triggerRate": 0.35,
    "multiTarget": false,
    "startRound": 1
  },
  {
    "id": "po_zhen_cui_jian",
    "name": "破阵催坚",
    "subType": "主动",
    "quality": "橙",
    "description": "对敌方群体造成兵刃伤害(武力差影响),并降低其统率和智力,持续2回合。",
    "source": "文丑传承",
    "sourceType": "传承",
    "carrierIds": [],
    "triggerRate": 0.35,
    "multiTarget": true,
    "startRound": 1
  },
  {
    "id": "huo_chi_yuan_liao",
    "name": "火炽原燎",
    "subType": "主动",
    "quality": "橙",
    "description": "对敌方群体造成谋略伤害(智力差影响),并使其陷入灼烧,持续1回合。",
    "source": "黄忠传承",
    "sourceType": "传承",
    "carrierIds": [],
    "triggerRate": 0.35,
    "multiTarget": true,
    "startRound": 1
  },
  {
    "id": "shi_bie_san_ri",
    "name": "士别三日",
    "subType": "被动",
    "quality": "橙",
    "description": "战斗前3回合积累属性,4回合后获得属性大幅提升,并获得连击/会心状态。",
    "source": "鲁肃传承",
    "sourceType": "传承",
    "carrierIds": [],
    "triggerRate": null,
    "multiTarget": false,
    "startRound": 1
  },
  {
    "id": "jie_li_zuo_mou",
    "name": "竭力佐谋",
    "subType": "指挥",
    "quality": "橙",
    "description": "战斗开始时,使一名我方武将获得谋略提升和增伤属性,持续全场。",
    "source": "左慈传承",
    "sourceType": "传承",
    "carrierIds": [],
    "triggerRate": null,
    "multiTarget": false,
    "startRound": 1
  },
  {
    "id": "bing_feng",
    "name": "兵锋",
    "subType": "突击",
    "quality": "橙",
    "description": "普通攻击后,对目标额外造成一次兵刃伤害(武力差影响)。",
    "source": "徐晃传承",
    "sourceType": "传承",
    "carrierIds": [],
    "triggerRate": 0.35,
    "multiTarget": false,
    "startRound": 1
  },
  {
    "id": "wu_feng_zhen",
    "name": "武峰阵",
    "subType": "阵法",
    "quality": "橙",
    "description": "战斗中,主将与副将分担所受伤害;副将获得减伤,主将获得增伤。",
    "source": "通用",
    "sourceType": "通用",
    "carrierIds": ["zhuge_liang", "liu_bei", "zhang_fei", "guan_yu", "zhao_yun"],
    "triggerRate": null,
    "multiTarget": true,
    "startRound": 1
  },
  {
    "id": "xi_liang_tie_qi",
    "name": "西凉铁骑",
    "subType": "兵种",
    "quality": "橙",
    "description": "骑兵专属:全队骑兵获得属性提升,战斗中造成额外兵刃伤害。",
    "source": "马超传承",
    "sourceType": "传承",
    "carrierIds": [],
    "triggerRate": null,
    "multiTarget": true,
    "startRound": 1
  },
  {
    "id": "bei_she_gui_che",
    "name": "杯蛇鬼车",
    "subType": "主动",
    "quality": "橙",
    "description": "对敌方群体造成谋略伤害(智力差影响),并为我方群体恢复兵力(智力影响)。",
    "source": "曹操传承",
    "sourceType": "传承",
    "carrierIds": [],
    "triggerRate": 0.35,
    "multiTarget": true,
    "startRound": 2
  },
  {
    "id": "chen_sha_jue_shui",
    "name": "沉沙决水",
    "subType": "主动",
    "quality": "橙",
    "description": "对敌方群体造成谋略伤害(智力差影响),并使其陷入水攻,持续2回合。",
    "source": "庞统传承",
    "sourceType": "传承",
    "carrierIds": [],
    "triggerRate": 0.35,
    "multiTarget": true,
    "startRound": 2
  },
  {
    "id": "yong_wu_tong_shen",
    "name": "用武通神",
    "subType": "主动",
    "quality": "橙",
    "description": "对随机敌方单体造成谋略伤害(智力差影响),共发动两次,间隔1回合。",
    "source": "诸葛亮传承",
    "sourceType": "传承",
    "carrierIds": ["zhuge_liang"],
    "triggerRate": 0.35,
    "multiTarget": false,
    "startRound": 1
  },
  {
    "id": "xing_ji_jun_lve",
    "name": "形机军略",
    "subType": "主动",
    "quality": "橙",
    "description": "对随机敌方单体造成谋略伤害(智力差影响),并使其受到谋略伤害提升,持续2回合。",
    "source": "周瑜传承",
    "sourceType": "传承",
    "carrierIds": [],
    "triggerRate": 0.35,
    "multiTarget": false,
    "startRound": 2
  },
  {
    "id": "shi_zhi_bu_yi",
    "name": "矢志不移",
    "subType": "主动",
    "quality": "紫",
    "description": "对随机敌方单体造成兵刃伤害(武力差影响),并使其陷入溃逃,持续1回合。",
    "source": "通用拆解",
    "sourceType": "拆解",
    "carrierIds": [],
    "triggerRate": 0.35,
    "multiTarget": false,
    "startRound": 1
  },
  {
    "id": "yong_guan_san_jun",
    "name": "勇冠三军",
    "subType": "主动",
    "quality": "橙",
    "description": "对敌方群体造成兵刃伤害(武力差影响),并使我方单体获得连击状态,持续1回合。",
    "source": "许褚传承",
    "sourceType": "传承",
    "carrierIds": [],
    "triggerRate": 0.35,
    "multiTarget": true,
    "startRound": 1
  },
  {
    "id": "yi_li_ju_shou",
    "name": "一力拒守",
    "subType": "主动",
    "quality": "紫",
    "description": "对随机敌方单体造成兵刃伤害(武力差影响),并使我方单体获得减伤,持续1回合。",
    "source": "通用拆解",
    "sourceType": "拆解",
    "carrierIds": [],
    "triggerRate": 0.35,
    "multiTarget": false,
    "startRound": 1
  },
  {
    "id": "yi_dan_zhong_xin",
    "name": "义胆忠心",
    "subType": "被动",
    "quality": "紫",
    "description": "战斗开始时,使自身获得属性提升;受到致命伤害时有概率免疫本次伤害。",
    "source": "通用拆解",
    "sourceType": "拆解",
    "carrierIds": [],
    "triggerRate": null,
    "multiTarget": false,
    "startRound": 1
  },
  {
    "id": "xue_jian_xuan_yuan",
    "name": "血荐轩辕",
    "subType": "被动",
    "quality": "橙",
    "description": "自身每损失一定兵力,会获得属性提升;兵力较低时获得暴击与增伤。",
    "source": "刘备传承",
    "sourceType": "传承",
    "carrierIds": ["liu_bei"],
    "triggerRate": null,
    "multiTarget": false,
    "startRound": 1
  },
  {
    "id": "xiao_yong_wu_pi",
    "name": "骁勇无匹",
    "subType": "被动",
    "quality": "橙",
    "description": "普攻后获得武力提升(可叠加);自身武力越高,普攻伤害越高。",
    "source": "张飞传承",
    "sourceType": "传承",
    "carrierIds": ["zhang_fei"],
    "triggerRate": null,
    "multiTarget": false,
    "startRound": 1
  },
  {
    "id": "gui_shen_mo_ce",
    "name": "鬼神莫测",
    "subType": "被动",
    "quality": "橙",
    "description": "主动战法发动时,有概率使本次伤害提升,并使自身获得谋略伤害加成。",
    "source": "司马懿传承",
    "sourceType": "传承",
    "carrierIds": [],
    "triggerRate": null,
    "multiTarget": false,
    "startRound": 1
  },
  {
    "id": "jian_ti_qiang_shen",
    "name": "健体强身",
    "subType": "被动",
    "quality": "紫",
    "description": "战斗开始时,使自身获得统率与智力提升,持续全场。",
    "source": "通用拆解",
    "sourceType": "拆解",
    "carrierIds": [],
    "triggerRate": null,
    "multiTarget": false,
    "startRound": 1
  },
  {
    "id": "xu_shi_dai_fa",
    "name": "蓄势待发",
    "subType": "被动",
    "quality": "蓝",
    "description": "战斗前2回合获得属性积累,第3回合起属性显著提升,持续全场。",
    "source": "通用拆解",
    "sourceType": "拆解",
    "carrierIds": [],
    "triggerRate": null,
    "multiTarget": false,
    "startRound": 1
  },
  {
    "id": "ba_men_jin_suo_zhen",
    "name": "八门金锁阵",
    "subType": "指挥",
    "quality": "橙",
    "description": "战斗开始时,使敌方群体受到的伤害提升,我方主将获得先手与减伤,持续3回合。",
    "source": "通用拆解",
    "sourceType": "拆解",
    "carrierIds": [],
    "triggerRate": null,
    "multiTarget": false,
    "startRound": 1
  },
  {
    "id": "zheng_zhuang_dai_fa",
    "name": "整装待发",
    "subType": "指挥",
    "quality": "紫",
    "description": "战斗开始时,使我方群体获得减伤,持续3回合;每回合开始恢复少量兵力。",
    "source": "通用拆解",
    "sourceType": "拆解",
    "carrierIds": [],
    "triggerRate": null,
    "multiTarget": false,
    "startRound": 1
  },
  {
    "id": "shi_zheng_xian_fu",
    "name": "士争先赴",
    "subType": "指挥",
    "quality": "蓝",
    "description": "战斗开始时,使我方群体获得属性小幅提升,持续全场。",
    "source": "通用拆解",
    "sourceType": "拆解",
    "carrierIds": [],
    "triggerRate": null,
    "multiTarget": false,
    "startRound": 1
  },
  {
    "id": "bao_lian_si_fang",
    "name": "暴敛四方",
    "subType": "突击",
    "quality": "橙",
    "description": "普通攻击后,对敌方群体造成兵刃伤害(武力差影响),并使其陷入混乱,持续1回合。",
    "source": "董卓传承",
    "sourceType": "传承",
    "carrierIds": [],
    "triggerRate": 0.35,
    "multiTarget": true,
    "startRound": 1
  },
  {
    "id": "duan_bing_xiang_jie",
    "name": "短兵相接",
    "subType": "突击",
    "quality": "紫",
    "description": "普通攻击后,对目标额外造成一次兵刃伤害(武力差影响),并使其陷入缴械。",
    "source": "通用拆解",
    "sourceType": "拆解",
    "carrierIds": [],
    "triggerRate": 0.35,
    "multiTarget": false,
    "startRound": 1
  },
  {
    "id": "qie_zhen_duo_shuai",
    "name": "怯阵夺帅",
    "subType": "突击",
    "quality": "橙",
    "description": "普通攻击后,对敌方主将额外造成兵刃伤害,并使其陷入虚弱,持续1回合。",
    "source": "吕布传承",
    "sourceType": "传承",
    "carrierIds": [],
    "triggerRate": 0.35,
    "multiTarget": false,
    "startRound": 1
  },
  {
    "id": "feng_shi_zhen",
    "name": "锋矢阵",
    "subType": "阵法",
    "quality": "橙",
    "description": "战斗中,主将获得增伤,副将获得减伤;主将受到的伤害由副将分担一部分。",
    "source": "通用拆解",
    "sourceType": "拆解",
    "carrierIds": [],
    "triggerRate": null,
    "multiTarget": false,
    "startRound": 1
  },
  {
    "id": "he_yi_zhen",
    "name": "鹤翼阵",
    "subType": "阵法",
    "quality": "紫",
    "description": "战斗中,副将获得增伤,主将获得减伤;全体获得速度提升。",
    "source": "通用拆解",
    "sourceType": "拆解",
    "carrierIds": [],
    "triggerRate": null,
    "multiTarget": false,
    "startRound": 1
  },
  {
    "id": "yu_lin_zhen",
    "name": "鱼鳞阵",
    "subType": "阵法",
    "quality": "紫",
    "description": "战斗中,副将获得减伤,主将获得增伤;全体普攻伤害提升。",
    "source": "通用拆解",
    "sourceType": "拆解",
    "carrierIds": [],
    "triggerRate": null,
    "multiTarget": false,
    "startRound": 1
  },
  {
    "id": "ba_gua_zhen",
    "name": "八卦阵",
    "subType": "阵法",
    "quality": "橙",
    "description": "战斗中,敌方受到的谋略伤害提升,我方受到的谋略伤害降低,持续全场。",
    "source": "诸葛亮传承",
    "sourceType": "传承",
    "carrierIds": ["zhuge_liang"],
    "triggerRate": null,
    "multiTarget": false,
    "startRound": 1
  },
  {
    "id": "yan_xing_zhen",
    "name": "雁形阵",
    "subType": "阵法",
    "quality": "蓝",
    "description": "战斗中,我方全体获得速度提升,普攻后有概率获得闪避。",
    "source": "通用拆解",
    "sourceType": "拆解",
    "carrierIds": [],
    "triggerRate": null,
    "multiTarget": false,
    "startRound": 1
  },
  {
    "id": "da_yan_zhen",
    "name": "大雁阵",
    "subType": "阵法",
    "quality": "蓝",
    "description": "战斗中,副将获得先手与减伤,主将获得增伤,持续全场。",
    "source": "通用拆解",
    "sourceType": "拆解",
    "carrierIds": [],
    "triggerRate": null,
    "multiTarget": false,
    "startRound": 1
  },
  {
    "id": "da_ji_shi",
    "name": "大戟士",
    "subType": "兵种",
    "quality": "橙",
    "description": "枪兵专属:全队枪兵获得属性提升,普攻有概率造成额外兵刃伤害。",
    "source": "通用拆解",
    "sourceType": "拆解",
    "carrierIds": [],
    "triggerRate": null,
    "multiTarget": false,
    "startRound": 1
  },
  {
    "id": "fei_xiong_jun",
    "name": "飞熊军",
    "subType": "兵种",
    "quality": "紫",
    "description": "骑兵专属:全队骑兵获得属性提升,战斗中造成额外兵刃伤害。",
    "source": "通用拆解",
    "sourceType": "拆解",
    "carrierIds": [],
    "triggerRate": null,
    "multiTarget": false,
    "startRound": 1
  },
  {
    "id": "bai_ma_yi_cong",
    "name": "白马义从",
    "subType": "兵种",
    "quality": "橙",
    "description": "弓兵专属:全队弓兵获得属性提升,普攻有概率获得连击状态。",
    "source": "公孙瓒传承",
    "sourceType": "传承",
    "carrierIds": [],
    "triggerRate": null,
    "multiTarget": false,
    "startRound": 1
  },
  {
    "id": "wu_dang_fei_jun",
    "name": "无当飞军",
    "subType": "兵种",
    "quality": "橙",
    "description": "弓兵专属:全队弓兵获得属性提升,主动战法发动时获得增伤。",
    "source": "诸葛亮传承",
    "sourceType": "传承",
    "carrierIds": ["zhuge_liang"],
    "triggerRate": null,
    "multiTarget": false,
    "startRound": 1
  },
  {
    "id": "teng_jia_bing",
    "name": "藤甲兵",
    "subType": "兵种",
    "quality": "橙",
    "description": "盾兵专属:全队盾兵获得属性提升,受到兵刃伤害大幅降低。",
    "source": "通用拆解",
    "sourceType": "拆解",
    "carrierIds": [],
    "triggerRate": null,
    "multiTarget": false,
    "startRound": 1
  },
  {
    "id": "hu_bao_qi",
    "name": "虎豹骑",
    "subType": "兵种",
    "quality": "橙",
    "description": "骑兵专属:全队骑兵获得属性提升,普攻有概率造成额外兵刃伤害。",
    "source": "通用拆解",
    "sourceType": "拆解",
    "carrierIds": [],
    "triggerRate": null,
    "multiTarget": false,
    "startRound": 1
  }
]
